LICENSE
README.md
setup.py
itchio/DownloadKey.py
itchio/Earnings.py
itchio/Game.py
itchio/GameCollection.py
itchio/Purchase.py
itchio/Session.py
itchio/User.py
itchio/UserCollection.py
itchio/__init__.py
itchio/utility.py
itchio.egg-info/PKG-INFO
itchio.egg-info/SOURCES.txt
itchio.egg-info/dependency_links.txt
itchio.egg-info/requires.txt
itchio.egg-info/top_level.txt
tests/test.py