Metadata-Version: 2.1
Name: itchio
Version: 1.1.3
Summary: Interact with the REST-API of itch.io
Home-page: https://github.com/Tch1b0/itchio-lib
Author: Johannes Pour
Author-email: jpour3006@gmail.com
License: MIT
Requires-Python: >3.5
License-File: LICENSE
Requires-Dist: requests>=2.31.0
